<rcs>
	<rc id="1">
		<button label="POWER" pos="48,19" />
		<button label="1" pos="46,111" />
		<button label="2" pos="74,111" />
		<button label="3" pos="101,111" />
		<button label="4" pos="46,131" />
		<button label="5" pos="74,131" />
		<button label="6" pos="101,131" />
		<button label="7" pos="46,152" />
		<button label="8" pos="74,152" />
		<button label="9" pos="101,152" />
		<button label="ARROWLEFT" pos="46,171" />
		<button label="0" pos="74,171" />
		<button label="ARROWRIGHT" pos="101,171" />
		<button label="VOL+" pos="42,290" />
		<button label="VOL-" pos="42,325" />
		<button label="MUTE" pos="100,18" />
		<button label="EXIT" pos="105,259" />
		<button label="BOUQUET+" pos="104,289" />
		<button label="BOUQUET-" pos="104,324" />
		<button label="INFO" pos="105,199" />
		<button label="MENU" pos="42,259" />
		<button label="OK" pos="74,230" />
		<button label="UP" pos="74,207" />
		<button label="DOWN" pos="74,255" />
		<button label="LEFT" pos="49,230" />
		<button label="RIGHT" pos="97,230" />
		<button label="HELP" pos="103,404" />
		<button label="PVR" pos="73,344" />
		<button label="RED" pos="43,440" />
		<button label="GREEN" pos="63,440" />
		<button label="YELLOW" pos="84,440" />
		<button label="BLUE" pos="105,440" />
		<button label="REWIND" pos="47,369" />
		<button label="PLAYPAUSE" pos="74,369" />
		<button label="STOP" pos="74,388" />
		<button label="FORWARD" pos="101,369" />
		<button label="TV" pos="41,345" />
		<button label="RADIO" pos="105,343" />
		<button label="TEXT" pos="44,423" />
		<button label="RECORD" pos="73,344" />
	</rc>
</rcs>
