<rcs>
	<rc id="2">
		<button label="POWER" pos="25,46" />
		<button label="MUTE" pos="95,46" />
		<button label="HELP" pos="75,71" />
		<button label="1" pos="23,95" />
		<button label="2" pos="62,95" />
		<button label="3" pos="99,95" />
		<button label="4" pos="23,114" />
		<button label="5" pos="62,114" />
		<button label="6" pos="99,114" />
		<button label="7" pos="23,134" />
		<button label="8" pos="62,134" />
		<button label="9" pos="99,134" />
		<button label="ARROWLEFT" pos="23,153" />
		<button label="0" pos="62,153" />
		<button label="ARROWRIGHT" pos="99,153" />
		<button label="VOL+" pos="22,181" />
		<button label="VOL-" pos="22,212" />
		<button label="BOUQUET+" pos="100,181" />
		<button label="BOUQUET-" pos="100,212" />
		<button label="EPG" pos="62,212" />
		<button label="MENU" pos="22,342" />
		<button label="EXIT" pos="100,342" />
		<button label="OK" pos="62,303" />
		<button label="UP" pos="62,268" />
		<button label="DOWN" pos="62,340" />
		<button label="LEFT" pos="25,303" />
		<button label="RIGHT" pos="97,303" />
		<button label="INFO" pos="23,266" />
		<button label="BACK" pos="100,266" />
		<button label="RED" pos="20,365" />
		<button label="GREEN" pos="48,365" />
		<button label="YELLOW" pos="74,365" />
		<button label="BLUE" pos="102,365" />
		<button label="REWIND" pos="20,389" />
		<button label="PLAY" pos="48,389" />
		<button label="PAUSE" pos="74,389" />
		<button label="FASTFORWARD" pos="102,389" />
		<button label="AUDIO" pos="20,405" />
		<button label="STOP" pos="48,405" />
		<button label="RECORD" pos="74,405" />
		<button label="PVR" pos="62,177" />
		<button label="TEXT" pos="20,424" />
		<button label="SUBTITLE" pos="48,424" />
		<button label="TV" pos="74,424" />
		<button label="RADIO" pos="74,424" />
		<button label="FAVORITES" pos="102,424" />
	</rc>
</rcs>
